Metadata-Version: 2.4
Name: fastapi-slim
Version: 0.128.0
Summary: FastAPI framework, high performance, easy to learn, fast to code, ready for production
Author-Email: =?utf-8?q?Sebasti=C3=A1n_Ram=C3=ADrez?= <tiangolo@gmail.com>
License-Expression: MIT
License-File: LICENSE
Classifier: Intended Audience :: Information Technology
Classifier: Intended Audience :: System Administrators
Classifier: Operating System :: OS Independent
Classifier: Programming Language :: Python :: 3
Classifier: Programming Language :: Python
Classifier: Topic :: Internet
Classifier: Topic :: Software Development :: Libraries :: Application Frameworks
Classifier: Topic :: Software Development :: Libraries :: Python Modules
Classifier: Topic :: Software Development :: Libraries
Classifier: Topic :: Software Development
Classifier: Typing :: Typed
Classifier: Development Status :: 4 - Beta
Classifier: Environment :: Web Environment
Classifier: Framework :: AsyncIO
Classifier: Framework :: FastAPI
Classifier: Framework :: Pydantic
Classifier: Framework :: Pydantic :: 2
Classifier: Intended Audience :: Developers
Classifier: Programming Language :: Python :: 3 :: Only
Classifier: Programming Language :: Python :: 3.9
Classifier: Programming Language :: Python :: 3.10
Classifier: Programming Language :: Python :: 3.11
Classifier: Programming Language :: Python :: 3.12
Classifier: Programming Language :: Python :: 3.13
Classifier: Programming Language :: Python :: 3.14
Classifier: Topic :: Internet :: WWW/HTTP :: HTTP Servers
Classifier: Topic :: Internet :: WWW/HTTP
Project-URL: Homepage, https://github.com/fastapi/fastapi
Project-URL: Documentation, https://fastapi.tiangolo.com/
Project-URL: Repository, https://github.com/fastapi/fastapi
Project-URL: Issues, https://github.com/fastapi/fastapi/issues
Project-URL: Changelog, https://fastapi.tiangolo.com/release-notes/
Requires-Python: >=3.9
Requires-Dist: starlette<0.51.0,>=0.40.0
Requires-Dist: pydantic>=2.7.0
Requires-Dist: typing-extensions>=4.8.0
Requires-Dist: annotated-doc>=0.0.2
Provides-Extra: standard
Requires-Dist: fastapi-cli[standard]>=0.0.8; extra == "standard"
Requires-Dist: httpx<1.0.0,>=0.23.0; extra == "standard"
Requires-Dist: jinja2>=3.1.5; extra == "standard"
Requires-Dist: python-multipart>=0.0.18; extra == "standard"
Requires-Dist: email-validator>=2.0.0; extra == "standard"
Requires-Dist: uvicorn[standard]>=0.12.0; extra == "standard"
Requires-Dist: pydantic-settings>=2.0.0; extra == "standard"
Requires-Dist: pydantic-extra-types>=2.0.0; extra == "standard"
Provides-Extra: standard-no-fastapi-cloud-cli
Requires-Dist: fastapi-cli[standard-no-fastapi-cloud-cli]>=0.0.8; extra == "standard-no-fastapi-cloud-cli"
Requires-Dist: httpx<1.0.0,>=0.23.0; extra == "standard-no-fastapi-cloud-cli"
Requires-Dist: jinja2>=3.1.5; extra == "standard-no-fastapi-cloud-cli"
Requires-Dist: python-multipart>=0.0.18; extra == "standard-no-fastapi-cloud-cli"
Requires-Dist: email-validator>=2.0.0; extra == "standard-no-fastapi-cloud-cli"
Requires-Dist: uvicorn[standard]>=0.12.0; extra == "standard-no-fastapi-cloud-cli"
Requires-Dist: pydantic-settings>=2.0.0; extra == "standard-no-fastapi-cloud-cli"
Requires-Dist: pydantic-extra-types>=2.0.0; extra == "standard-no-fastapi-cloud-cli"
Provides-Extra: all
Requires-Dist: fastapi-cli[standard]>=0.0.8; extra == "all"
Requires-Dist: httpx<1.0.0,>=0.23.0; extra == "all"
Requires-Dist: jinja2>=3.1.5; extra == "all"
Requires-Dist: python-multipart>=0.0.18; extra == "all"
Requires-Dist: itsdangerous>=1.1.0; extra == "all"
Requires-Dist: pyyaml>=5.3.1; extra == "all"
Requires-Dist: ujson!=4.0.2,!=4.1.0,!=4.2.0,!=4.3.0,!=5.0.0,!=5.1.0,>=4.0.1; extra == "all"
Requires-Dist: orjson>=3.2.1; extra == "all"
Requires-Dist: email-validator>=2.0.0; extra == "all"
Requires-Dist: uvicorn[standard]>=0.12.0; extra == "all"
Requires-Dist: pydantic-settings>=2.0.0; extra == "all"
Requires-Dist: pydantic-extra-types>=2.0.0; extra == "all"
